{
  "publicPath": "/dist/",
  "all": [
    "0.1db7b12525d9375fb913.js",
    "1.50390c819c86637be694.js",
    "2.a0376ebb1116fb3413b0.js",
    "vendor.87c5eed709b22da7e20a.js",
    "app.8f9eed8083d5bb50b501.js",
    "manifest.07421cb26899452c08a3.js",
    "common.8f9eed8083d5bb50b501.css"
  ],
  "initial": [
    "manifest.07421cb26899452c08a3.js",
    "vendor.87c5eed709b22da7e20a.js",
    "app.8f9eed8083d5bb50b501.js"
  ],
  "async": [
    "0.1db7b12525d9375fb913.js",
    "1.50390c819c86637be694.js",
    "2.a0376ebb1116fb3413b0.js"
  ],
  "modules": {
    "39860197": [
      3
    ],
    "50387680": [
      3
    ],
    "59113445": [
      3
    ],
    "60595713": [
      3
    ],
    "68920345": [
      3
    ],
    "72786557": [
      3
    ],
    "97591974": [
      3
    ],
    "b4985ffc": [
      3
    ],
    "30c72fd2": [
      3
    ],
    "2282f4f4": [
      3
    ],
    "0ef82b0e": [
      3
    ],
    "773cdcc0": [
      3
    ],
    "1c838c82": [
      3
    ],
    "512bd280": [
      3
    ],
    "4ed332a7": [
      3
    ],
    "324f3028": [
      3
    ],
    "e16862ac": [
      3
    ],
    "69ef06df": [
      3
    ],
    "6dae6e26": [
      3
    ],
    "d5ca3ade": [
      3
    ],
    "ff607e42": [
      3
    ],
    "3376270b": [
      3
    ],
    "74f5336c": [
      3
    ],
    "a8d790fe": [
      3
    ],
    "3c7ab036": [
      3
    ],
    "8edb9554": [
      3
    ],
    "1787ede4": [
      3
    ],
    "0bdf3885": [
      3
    ],
    "2f7c18a0": [
      3
    ],
    "9f6ba23c": [
      3
    ],
    "19638bd3": [
      3
    ],
    "9abc4296": [
      3
    ],
    "079d8e6a": [
      3
    ],
    "db015bec": [
      3
    ],
    "7af7970b": [
      3
    ],
    "6ae1a439": [
      3
    ],
    "b2e0f028": [
      3
    ],
    "9d551eee": [
      3
    ],
    "0e855331": [
      3
    ],
    "a48ffcb2": [
      3
    ],
    "46fe8508": [
      3
    ],
    "999fc874": [
      3
    ],
    "f62ff0d6": [
      3
    ],
    "ac798b70": [
      3
    ],
    "ecbe06f4": [
      3
    ],
    "d5aaa9d2": [
      3
    ],
    "6bfc559e": [
      3
    ],
    "4c02e697": [
      3
    ],
    "567d6ebb": [
      3
    ],
    "64277be0": [
      3
    ],
    "3ef701e2": [
      3
    ],
    "7dcec8d4": [
      3
    ],
    "2fd375a5": [
      3
    ],
    "4fff2603": [
      3
    ],
    "6da96cb1": [
      3
    ],
    "59da2196": [
      3
    ],
    "0ad441e3": [
      3
    ],
    "387e6145": [
      3
    ],
    "7fb96c14": [
      3
    ],
    "79c13ed5": [
      3
    ],
    "6f94bab5": [
      3
    ],
    "9b8ab2e8": [
      3
    ],
    "6de257c8": [
      3
    ],
    "5dd42174": [
      4,
      6
    ],
    "5bf0382e": [
      4,
      6
    ],
    "d0d87d16": [
      4,
      6
    ],
    "62507d3e": [
      3
    ],
    "59199e19": [
      3
    ],
    "4a309a4a": [
      3
    ],
    "7f4a6003": [
      4,
      6
    ],
    "6e91bd2f": [
      3
    ],
    "827c3e5c": [
      3
    ],
    "07524bae": [
      4,
      6
    ],
    "c6114848": [
      3
    ],
    "5cef3c29": [
      3
    ],
    "7e668bb4": [
      3
    ],
    "02cf42e7": [
      3
    ],
    "451ff915": [
      3
    ],
    "97a1f524": [
      3
    ],
    "e6f53960": [
      3
    ],
    "64209b28": [
      3
    ],
    "76afc644": [
      3
    ],
    "3fa2c338": [
      3
    ],
    "7629c46a": [
      3
    ],
    "2569f3c1": [
      3
    ],
    "0110e1d5": [
      3
    ],
    "ccd7c314": [
      3
    ],
    "168bf304": [
      3
    ],
    "5372b107": [
      3
    ],
    "468bf38a": [
      3
    ],
    "61620fe0": [
      3
    ],
    "119352a0": [
      3
    ],
    "013d4d92": [
      3
    ],
    "7b1f9e11": [
      3
    ],
    "743bffdf": [
      3
    ],
    "8b3b3e50": [
      3
    ],
    "cc19d3e2": [
      3
    ],
    "22e39af5": [
      3
    ],
    "096e5e80": [
      3
    ],
    "945e0c94": [
      3
    ],
    "c728f3d2": [
      3
    ],
    "4ba47825": [
      3
    ],
    "b4babf3c": [
      3
    ],
    "022c5c54": [
      3
    ],
    "2778a4a3": [
      3
    ],
    "e55ca16e": [
      3
    ],
    "8c8a58dc": [
      3
    ],
    "3bc24638": [
      3
    ],
    "4a0dc7f8": [
      3
    ],
    "54d74fb9": [
      3
    ],
    "a674d2d4": [
      3
    ],
    "1d199d25": [
      3
    ],
    "73c3a50d": [
      3
    ],
    "1fe04a0e": [
      3
    ],
    "7848c5e0": [
      3
    ],
    "d8570e5e": [
      3
    ],
    "746dbff2": [
      3
    ],
    "2341d244": [
      3
    ],
    "771bafe1": [
      3
    ],
    "124986db": [
      3
    ],
    "b9d4c138": [
      3
    ],
    "040fe5c8": [
      3
    ],
    "550a7fd6": [
      3
    ],
    "0aae668c": [
      3
    ],
    "5bdabbba": [
      4,
      6
    ],
    "3c638556": [
      3
    ],
    "7ebd74b6": [
      3
    ],
    "9bed93e0": [
      1
    ],
    "6b4fa2f8": [
      1
    ],
    "4a2be254": [
      1
    ],
    "3bbbf860": [
      1
    ],
    "f345513e": [
      0
    ],
    "c2a76056": [
      0
    ],
    "10d8577a": [
      0
    ],
    "33ed1a92": [
      0
    ],
    "20800eab": [
      0
    ],
    "0ef5ad1f": [
      0
    ],
    "8f0548e4": [
      2
    ],
    "5e6757fc": [
      2
    ],
    "72393ffc": [
      1
    ],
    "89d29c1e": [
      0
    ],
    "3751d658": [
      2
    ]
  }
}